pymcworld/__init__.py
pymcworld/block.py
pymcworld/chunk.py
pymcworld/gamerules.py
pymcworld/nbt.py
pymcworld/option.py
pymcworld/palette.py
pymcworld/region.py
pymcworld/section.py
pymcworld/shape.py
pymcworld/structure.py
pymcworld/world.py
pymcworld-1.0.2.dist-info/LICENSE
pymcworld-1.0.2.dist-info/METADATA
pymcworld-1.0.2.dist-info/WHEEL
pymcworld-1.0.2.dist-info/top_level.txt
pymcworld-1.0.2.dist-info/RECORD
