Metadata-Version: 2.1
Name: pymcworld
Version: 1.0.2
Summary: Simple Minecraft world editor
Home-page: https://github.com/gullyn/pymcworld
Author: gullyn
Author-email: gullyn.games@gmail.com
License: UNKNOWN
Platform: UNKNOWN
Classifier: Programming Language :: Python :: 3
Classifier: License :: OSI Approved :: MIT License
Classifier: Operating System :: OS Independent
Requires-Python: >=3.6
